qrcode_term/__init__.py
qrcode_term/qrcode_term.py
qrcode_term-0.0.1.dist-info/LICENSE
qrcode_term-0.0.1.dist-info/METADATA
qrcode_term-0.0.1.dist-info/WHEEL
qrcode_term-0.0.1.dist-info/top_level.txt
qrcode_term-0.0.1.dist-info/RECORD
