Metadata-Version: 2.1
Name: qrcode-term
Version: 0.0.1
Summary: QR code generator for terminal output
Home-page: https://github.com/agyx/qrcode_term
Author: agyx
Author-email: bm842@pm.me
License: UNKNOWN
Project-URL: Bug Tracker, https://github.com/agyx/qrcode_term/issues
Platform: UNKNOWN
Classifier: Programming Language :: Python :: 3
Classifier: License :: OSI Approved :: MIT License
Classifier: Operating System :: OS Independent
Requires-Python: >=3.6
License-File: LICENSE
Requires-Dist: qrcode
